ArabicNormalization/ArNormalization.py
ArabicNormalization/__init__.py
ArabicTextNormlzation-0.0.1.dist-info/METADATA
ArabicTextNormlzation-0.0.1.dist-info/WHEEL
ArabicTextNormlzation-0.0.1.dist-info/top_level.txt
ArabicTextNormlzation-0.0.1.dist-info/RECORD
