Metadata-Version: 2.1
Name: ArabicTextNormlzation
Version: 0.0.1
Summary: A small example package
Author-email: Example Author <yalhag@gmail.com>
Classifier: Programming Language :: Python :: 3
Classifier: License :: OSI Approved :: MIT License
Classifier: Operating System :: OS Independent
Requires-Python: >=3.7
